{
  "name": "Arial",
  "size": 100,
  "bold": false,
  "italic": false,
  "width": 1039,
  "height": 350,
  "characters": {
    "0":{"x":290,"y":96,"width":51,"height":73,"originX":-2,"originY":71,"advance":56},
    "1":{"x":99,"y":241,"width":46,"height":71,"originX":-6,"originY":70,"advance":56},
    "2":{"x":939,"y":96,"width":48,"height":72,"originX":-4,"originY":71,"advance":56},
    "3":{"x":341,"y":96,"width":51,"height":73,"originX":-2,"originY":71,"advance":56},
    "4":{"x":786,"y":96,"width":53,"height":72,"originX":-1,"originY":71,"advance":56},
    "5":{"x":839,"y":96,"width":50,"height":72,"originX":-3,"originY":70,"advance":56},
    "6":{"x":442,"y":96,"width":49,"height":73,"originX":-4,"originY":71,"advance":56},
    "7":{"x":987,"y":96,"width":48,"height":72,"originX":-4,"originY":71,"advance":56},
    "8":{"x":392,"y":96,"width":50,"height":73,"originX":-3,"originY":71,"advance":56},
    "9":{"x":491,"y":96,"width":49,"height":73,"originX":-3,"originY":71,"advance":56},
    " ":{"x":369,"y":312,"width":3,"height":3,"originX":1,"originY":1,"advance":28},
    "!":{"x":145,"y":241,"width":12,"height":71,"originX":-8,"originY":70,"advance":28},
    "\"":{"x":152,"y":312,"width":30,"height":24,"originX":-3,"originY":70,"advance":35},
    "#":{"x":718,"y":169,"width":58,"height":71,"originX":1,"originY":70,"advance":56},
    "$":{"x":362,"y":0,"width":55,"height":84,"originX":0,"originY":75,"advance":56},
    "%":{"x":0,"y":96,"width":85,"height":73,"originX":-2,"originY":71,"advance":89},
    "&":{"x":540,"y":96,"width":65,"height":72,"originX":-2,"originY":70,"advance":67},
    "'":{"x":182,"y":312,"width":12,"height":24,"originX":-4,"originY":70,"advance":19},
    "(":{"x":96,"y":0,"width":29,"height":96,"originX":-5,"originY":74,"advance":33},
    ")":{"x":66,"y":0,"width":30,"height":96,"originX":1,"originY":74,"advance":33},
    "*":{"x":49,"y":312,"width":39,"height":38,"originX":0,"originY":70,"advance":39},
    "+":{"x":987,"y":241,"width":52,"height":52,"originX":-3,"originY":60,"advance":58},
    ",":{"x":140,"y":312,"width":12,"height":26,"originX":-8,"originY":12,"advance":28},
    "-":{"x":281,"y":312,"width":27,"height":10,"originX":-3,"originY":32,"advance":33},
    ".":{"x":269,"y":312,"width":12,"height":13,"originX":-8,"originY":12,"advance":28},
    "/":{"x":709,"y":0,"width":30,"height":76,"originX":1,"originY":74,"advance":28},
    ":":{"x":871,"y":241,"width":12,"height":55,"originX":-8,"originY":54,"advance":28},
    ";":{"x":198,"y":241,"width":12,"height":68,"originX":-8,"originY":54,"advance":28},
    "<":{"x":883,"y":241,"width":52,"height":54,"originX":-3,"originY":60,"advance":58},
    "=":{"x":88,"y":312,"width":52,"height":35,"originX":-3,"originY":51,"advance":58},
    ">":{"x":935,"y":241,"width":52,"height":54,"originX":-3,"originY":60,"advance":58},
    "?":{"x":889,"y":96,"width":50,"height":72,"originX":-3,"originY":71,"advance":56},
    "@":{"x":274,"y":0,"width":88,"height":89,"originX":-6,"originY":74,"advance":102},
    "A":{"x":210,"y":169,"width":69,"height":71,"originX":1,"originY":70,"advance":67},
    "B":{"x":890,"y":169,"width":56,"height":71,"originX":-7,"originY":70,"advance":67},
    "C":{"x":224,"y":96,"width":66,"height":73,"originX":-4,"originY":71,"advance":72},
    "D":{"x":478,"y":169,"width":62,"height":71,"originX":-7,"originY":70,"advance":72},
    "E":{"x":776,"y":169,"width":57,"height":71,"originX":-7,"originY":70,"advance":67},
    "F":{"x":0,"y":241,"width":52,"height":71,"originX":-7,"originY":70,"advance":61},
    "G":{"x":156,"y":96,"width":68,"height":73,"originX":-4,"originY":71,"advance":78},
    "H":{"x":600,"y":169,"width":59,"height":71,"originX":-7,"originY":70,"advance":72},
    "I":{"x":157,"y":241,"width":12,"height":71,"originX":-8,"originY":70,"advance":28},
    "J":{"x":0,"y":169,"width":44,"height":72,"originX":0,"originY":70,"advance":50},
    "K":{"x":540,"y":169,"width":60,"height":71,"originX":-7,"originY":70,"advance":67},
    "L":{"x":52,"y":241,"width":47,"height":71,"originX":-7,"originY":70,"advance":56},
    "M":{"x":140,"y":169,"width":70,"height":71,"originX":-7,"originY":70,"advance":83},
    "N":{"x":659,"y":169,"width":59,"height":71,"originX":-7,"originY":70,"advance":72},
    "O":{"x":85,"y":96,"width":71,"height":73,"originX":-3,"originY":71,"advance":78},
    "P":{"x":946,"y":169,"width":56,"height":71,"originX":-7,"originY":70,"advance":67},
    "Q":{"x":203,"y":0,"width":71,"height":91,"originX":-3,"originY":71,"advance":78},
    "R":{"x":605,"y":96,"width":62,"height":72,"originX":-7,"originY":71,"advance":72},
    "S":{"x":915,"y":0,"width":61,"height":74,"originX":-3,"originY":72,"advance":67},
    "T":{"x":727,"y":96,"width":59,"height":72,"originX":-1,"originY":70,"advance":61},
    "U":{"x":667,"y":96,"width":60,"height":72,"originX":-6,"originY":70,"advance":72},
    "V":{"x":279,"y":169,"width":69,"height":71,"originX":1,"originY":70,"advance":67},
    "W":{"x":44,"y":169,"width":96,"height":71,"originX":1,"originY":70,"advance":94},
    "X":{"x":348,"y":169,"width":65,"height":71,"originX":-1,"originY":70,"advance":67},
    "Y":{"x":413,"y":169,"width":65,"height":71,"originX":-1,"originY":70,"advance":67},
    "Z":{"x":833,"y":169,"width":57,"height":71,"originX":-2,"originY":70,"advance":61},
    "[":{"x":148,"y":0,"width":22,"height":96,"originX":-6,"originY":74,"advance":28},
    "\\":{"x":739,"y":0,"width":30,"height":76,"originX":1,"originY":74,"advance":28},
    "]":{"x":125,"y":0,"width":23,"height":96,"originX":1,"originY":74,"advance":28},
    "^":{"x":0,"y":312,"width":49,"height":38,"originX":1,"originY":70,"advance":47},
    "_":{"x":308,"y":312,"width":61,"height":9,"originX":3,"originY":-12,"advance":56},
    "`":{"x":194,"y":312,"width":23,"height":17,"originX":-4,"originY":75,"advance":33},
    "a":{"x":210,"y":241,"width":54,"height":57,"originX":-3,"originY":55,"advance":56},
    "b":{"x":613,"y":0,"width":48,"height":76,"originX":-5,"originY":74,"advance":56},
    "c":{"x":411,"y":241,"width":46,"height":57,"originX":-3,"originY":55,"advance":50},
    "d":{"x":661,"y":0,"width":48,"height":76,"originX":-3,"originY":74,"advance":56},
    "e":{"x":264,"y":241,"width":50,"height":57,"originX":-3,"originY":55,"advance":56},
    "f":{"x":862,"y":0,"width":29,"height":75,"originX":0,"originY":74,"advance":28},
    "g":{"x":417,"y":0,"width":48,"height":77,"originX":-3,"originY":55,"advance":56},
    "h":{"x":816,"y":0,"width":46,"height":75,"originX":-5,"originY":74,"advance":56},
    "i":{"x":891,"y":0,"width":12,"height":75,"originX":-5,"originY":74,"advance":22},
    "j":{"x":170,"y":0,"width":21,"height":96,"originX":4,"originY":74,"advance":22},
    "k":{"x":769,"y":0,"width":47,"height":75,"originX":-5,"originY":74,"advance":50},
    "l":{"x":903,"y":0,"width":12,"height":75,"originX":-5,"originY":74,"advance":22},
    "m":{"x":457,"y":241,"width":73,"height":56,"originX":-5,"originY":55,"advance":83},
    "n":{"x":580,"y":241,"width":46,"height":56,"originX":-5,"originY":55,"advance":56},
    "o":{"x":314,"y":241,"width":50,"height":57,"originX":-3,"originY":55,"advance":56},
    "p":{"x":465,"y":0,"width":48,"height":77,"originX":-5,"originY":55,"advance":56},
    "q":{"x":513,"y":0,"width":48,"height":77,"originX":-3,"originY":55,"advance":56},
    "r":{"x":671,"y":241,"width":28,"height":56,"originX":-5,"originY":55,"advance":33},
    "s":{"x":364,"y":241,"width":47,"height":57,"originX":-1,"originY":55,"advance":50},
    "t":{"x":169,"y":241,"width":29,"height":68,"originX":0,"originY":66,"advance":28},
    "u":{"x":626,"y":241,"width":45,"height":56,"originX":-5,"originY":54,"advance":56},
    "v":{"x":775,"y":241,"width":52,"height":55,"originX":1,"originY":54,"advance":50},
    "w":{"x":699,"y":241,"width":76,"height":55,"originX":2,"originY":54,"advance":72},
    "x":{"x":530,"y":241,"width":50,"height":56,"originX":0,"originY":55,"advance":50},
    "y":{"x":561,"y":0,"width":52,"height":76,"originX":1,"originY":54,"advance":50},
    "z":{"x":827,"y":241,"width":44,"height":55,"originX":-3,"originY":54,"advance":50},
    "{":{"x":0,"y":0,"width":33,"height":96,"originX":0,"originY":74,"advance":33},
    "|":{"x":191,"y":0,"width":12,"height":96,"originX":-7,"originY":74,"advance":26},
    "}":{"x":33,"y":0,"width":33,"height":96,"originX":0,"originY":74,"advance":33},
    "~":{"x":217,"y":312,"width":52,"height":15,"originX":-3,"originY":41,"advance":58}
  }
}
